ployst_pubsub-0.1.dist-info/DESCRIPTION.rst
ployst_pubsub-0.1.dist-info/METADATA
ployst_pubsub-0.1.dist-info/RECORD
ployst_pubsub-0.1.dist-info/WHEEL
ployst_pubsub-0.1.dist-info/metadata.json
ployst_pubsub-0.1.dist-info/top_level.txt
pubsub/__init__.py
pubsub/client.py
pubsub/message.py
pubsub/tests/__init__.py
pubsub/tests/test_messages.py
pubsub/tests/test_pubsub_integration.py
